[
     {
          "id": 1,
          "cookieId": "undefined",
          "login": "undefined",
          "password": "undefined"
     },
     {
          "id": 2,
          "cookieId": "yMINbUihHmgRgSbxQyLO2",
          "login": "log",
          "password": "pass"
     },
     {
          "id": 3,
          "cookieId": "undefined",
          "login": "undefined",
          "password": "undefined"
     },
     {
          "id": 4,
          "cookieId": "undefined",
          "login": "undefined",
          "password": "undefined"
     },
     {
          "id": 5,
          "cookieId": "undefined",
          "login": "undefined",
          "password": "undefined"
     },
     {
          "id": 6,
          "cookieId": "undefined",
          "login": "undefined",
          "password": "undefined"
     },
     {
          "id": 7,
          "cookieId": "undefined",
          "login": "undefined",
          "password": "undefined"
     },
     {
          "id": 8,
          "cookieId": "undefined",
          "login": "undefined",
          "password": "undefined"
     },
     {
          "id": 9,
          "cookieId": "undefined",
          "login": "undefined",
          "password": "undefined"
     },
     {
          "id": 10,
          "cookieId": "undefined",
          "login": "undefined",
          "password": "undefined"
     },
     {
          "id": 11,
          "cookieId": "undefined",
          "login": "undefined",
          "password": "undefined"
     },
     {
          "id": 12,
          "cookieId": "undefined",
          "login": "undefined",
          "password": "undefined"
     },
     {
          "id": 13,
          "cookieId": "undefined",
          "login": "undefined",
          "password": "undefined"
     },
     {
          "id": 14,
          "cookieId": "undefined",
          "login": "undefined",
          "password": "undefined"
     },
     {
          "id": 15,
          "cookieId": "undefined",
          "login": "undefined",
          "password": "undefined"
     },
     {
          "id": 16,
          "cookieId": "undefined",
          "login": "undefined",
          "password": "undefined"
     }
]